judgesync/__init__.py
judgesync/alignment.py
judgesync/comparison.py
judgesync/data_loader.py
judgesync/judge.py
judgesync/metrics.py
judgesync/types.py
judgesync-0.1.0.dist-info/licenses/LICENSE
judgesync-0.1.0.dist-info/METADATA
judgesync-0.1.0.dist-info/WHEEL
judgesync-0.1.0.dist-info/top_level.txt
judgesync-0.1.0.dist-info/RECORD
