Metadata-Version: 2.4
Name: judgesync
Version: 0.1.0
Summary: A Python package for aligning LLM judges to human preferences
Author-email: James Asher <jamesasher@microsoft.com>
Project-URL: Homepage, https://github.com/jasher4994/judgesync
Project-URL: Bug Tracker, https://github.com/jasher4994/judgesync/issues
Keywords: llm,evaluation,alignment,judge,metrics,azure,openai
Classifier: Development Status :: 3 - Alpha
Classifier: Intended Audience :: Developers
Classifier: Programming Language :: Python :: 3
Classifier: Programming Language :: Python :: 3.9
Classifier: Programming Language :: Python :: 3.10
Classifier: Programming Language :: Python :: 3.11
Classifier: Programming Language :: Python :: 3.12
Requires-Python: >=3.9
License-File: LICENSE
Requires-Dist: pandas>=1.3.0
Requires-Dist: numpy>=1.21.0
Requires-Dist: scikit-learn>=1.0.0
Requires-Dist: openai>=1.0.0
Requires-Dist: azure-identity>=1.14.0
Requires-Dist: python-dotenv>=0.19.0
Requires-Dist: nest-asyncio>=1.5.0
Provides-Extra: dev
Requires-Dist: pytest>=8.0.0; extra == "dev"
Requires-Dist: pytest-cov>=4.0.0; extra == "dev"
Requires-Dist: ruff>=0.1.0; extra == "dev"
Requires-Dist: pre-commit>=3.5.0; extra == "dev"
Requires-Dist: mypy>=1.8.0; extra == "dev"
Requires-Dist: build>=1.0.0; extra == "dev"
Dynamic: license-file
